Metadata-Version: 2.1
Name: odoo-addon-l10n_br_base
Version: 18.0.1.2.2
Requires-Python: >=3.10
Requires-Dist: email-validator
Requires-Dist: erpbrasil.base
Requires-Dist: num2words
Requires-Dist: odoo==18.0.*
Requires-Dist: phonenumbers
Summary: Customization of base module for implementations in Brazil.
Home-page: https://github.com/OCA/l10n-brazil
License: AGPL-3
Author: Akretion,Odoo Community Association (OCA)
Author-email: support@odoo-community.org
Classifier: Programming Language :: Python
Classifier: Framework :: Odoo
Classifier: Framework :: Odoo :: 18.0
Classifier: License :: OSI Approved :: GNU Affero General Public License v3
Classifier: Development Status :: 6 - Mature
